lace/__init__.py
lace/__main__.py
lace/_version.py
lace/bloom_filter.py
lace/cli.py
lace/cli_simplified.py
lace/client.py
lace/constants.py
lace/monitor.py
lace/rsl.py
lace/run_tracker.py
lace/utils.py
lace/validators.py
lace/check/__init__.py
lace/check/attribution.py
lace/check/attribution_sampler.py
lace/check/classifier.py
lace/check/fingerprint.py
lace/check/policy_signals.py
lace/check/redact.py
lace/check/report.py
lace/check/sampler.py
lace/check/tui_review.py
lace/check/providers/__init__.py
lace/check/providers/openai_proxy.py
lace/cloud/__init__.py
lace/cloud/api.py
lace/config/compliance_constants.py
lace/config/manager.py
lace/preflight/__init__.py
lace/preflight/license_detector.py
lace/preflight/orchestrator.py
lace/preflight/pdf_analyzer.py
lace/preflight/pii_detector.py
lace/preflight/registry.py
lace/preflight/scanner.py
lace/preflight/verdict.py
lace/regulatory/__init__.py
lace/regulatory/scope.py
lace/schemas/__init__.py
lace/schemas/analysis.min.v1.json
lace/schemas/analysis.v1.1.json
lace/schemas/eu_answers_keys_v2025_09.md
lace/schemas/preflight.v0.1.json
lace/sds/__init__.py
lace/sds/aggregate.py
lace/sds/eu_answers.py
lace/sds/questions.py
lace/sds/scanner.py
lace/sds/schema.py
lace/tests/test_client_normalizer.py
lace/tests/test_manifest_privacy.py
lace/tests/test_privacy_guarantees.py
lace/wizard/__init__.py
lace/wizard/analyzer.py
lace/wizard/analyzer_minimal.py
lace/wizard/questions.py
lace/wizard/questions.yaml
lace/wizard/questions_scope.yaml
lace/wizard/serializer.py
lace/wizard/storage.py
lace/wizard/suggest.py
lace/wizard/templates.py
lace/wizard/schemas/enums.yaml
lace/wizard/schemas/eu_training_summary_2025_07.json
lace_client-0.7.7.dist-info/METADATA
lace_client-0.7.7.dist-info/WHEEL
lace_client-0.7.7.dist-info/entry_points.txt
lace_client-0.7.7.dist-info/top_level.txt
lace_client-0.7.7.dist-info/RECORD
