Metadata-Version: 2.4
Name: lace-client
Version: 0.7.7
Summary: Lace SDS generator (EU AI Act Article 53 public summary) — online-only CLI
Author: Matthew Hansen
License: Proprietary
Keywords: AI Act,SDS,EU,compliance,docx
Classifier: Programming Language :: Python :: 3
Classifier: Programming Language :: Python :: 3 :: Only
Classifier: Programming Language :: Python :: 3.11
Classifier: Environment :: Console
Classifier: License :: Other/Proprietary License
Classifier: Intended Audience :: Developers
Classifier: Topic :: Software Development :: Build Tools
Requires-Python: >=3.10
Requires-Dist: click<9,>=8.1
Requires-Dist: httpx<0.28,>=0.27
Requires-Dist: PyYAML<7,>=6
Requires-Dist: pathspec<0.13,>=0.12
Requires-Dist: jsonschema<5,>=4.22
